ddmail_backup_taker/__init__.py
ddmail_backup_taker/__main__.py
ddmail_backup_taker/backup.py
ddmail_backup_taker/validate_config.py
ddmail_backup_taker-0.0.1.dist-info/METADATA
ddmail_backup_taker-0.0.1.dist-info/WHEEL
ddmail_backup_taker-0.0.1.dist-info/entry_points.txt
ddmail_backup_taker-0.0.1.dist-info/licenses/LICENSE
ddmail_backup_taker-0.0.1.dist-info/RECORD
