Metadata-Version: 2.4
Name: ddmail_backup_taker
Version: 0.0.1
Summary: Program to take backups for the DDMail project.
Project-URL: Homepage, https://github.com/drzobin/ddmail_backup_taker
Project-URL: Issues, https://github.com/drzobin/ddmail_backup_taker/issues
Author-email: Robin Larsson <me@drz.se>
License-Expression: AGPL-3.0
License-File: LICENSE
Classifier: Operating System :: POSIX :: Linux
Classifier: Programming Language :: Python :: 3
Requires-Python: >=3.8
Requires-Dist: python-gnupg
Requires-Dist: requests
Requires-Dist: toml
Provides-Extra: dev
Requires-Dist: flake8; extra == 'dev'
Requires-Dist: hatchling; extra == 'dev'
Requires-Dist: pyright; extra == 'dev'
Requires-Dist: pytest; extra == 'dev'
Requires-Dist: pytest-cov; extra == 'dev'
Requires-Dist: python-gnupg; extra == 'dev'
Requires-Dist: requests; extra == 'dev'
Requires-Dist: ruff; extra == 'dev'
Requires-Dist: toml; extra == 'dev'
Requires-Dist: twine; extra == 'dev'
Provides-Extra: test
Requires-Dist: flake8; extra == 'test'
Requires-Dist: pytest; extra == 'test'
Requires-Dist: pytest-cov; extra == 'test'
Requires-Dist: python-gnupg; extra == 'test'
Requires-Dist: requests; extra == 'test'
Requires-Dist: toml; extra == 'test'
